{"description":"enterLocation|mysuit","passed":false,"pending":false,"os":"Windows","instanceId":16480,"browser":{"name":"chrome","version":"83.0.4103.106"},"message":["Error: Timeout - Async callback was not invoked within timeout specified by jasmine.DEFAULT_TIMEOUT_INTERVAL."],"trace":["Error: Timeout - Async callback was not invoked within timeout specified by jasmine.DEFAULT_TIMEOUT_INTERVAL.\n    at Timeout._onTimeout (C:\\Users\\mohit.jaiswal\\AppData\\Roaming\\npm\\node_modules\\protractor\\node_modules\\jasmine-core\\lib\\jasmine-core\\jasmine.js:4281:23)\n    at listOnTimeout (internal/timers.js:531:17)\n    at processTimers (internal/timers.js:475:7)"],"browserLogs":[{"level":"WARNING","message":"https://a0.muscache.com/airbnb/static/packages/9c0e-da28f557.js 1:62066 \"AirEvent has been deprecated, please consider using `logJitneyEvent()` method to report Jitney event.\"","timestamp":1592567083102,"type":""},{"level":"WARNING","message":"https://a0.muscache.com/airbnb/static/packages/9c0e-da28f557.js 1:62066 \"AirEvent has been deprecated, please consider using `logJitneyEvent()` method to report Jitney event.\"","timestamp":1592567083125,"type":""},{"level":"WARNING","message":"https://a0.muscache.com/airbnb/static/packages/9c0e-da28f557.js 1:62066 \"AirEvent has been deprecated, please consider using `logJitneyEvent()` method to report Jitney event.\"","timestamp":1592567083430,"type":""},{"level":"WARNING","message":"https://a0.muscache.com/airbnb/static/packages/9c0e-da28f557.js 1:62066 \"AirEvent has been deprecated, please consider using `logJitneyEvent()` method to report Jitney event.\"","timestamp":1592567083798,"type":""},{"level":"WARNING","message":"https://a0.muscache.com/airbnb/static/packages/9c0e-da28f557.js 1:62066 \"AirEvent has been deprecated, please consider using `logJitneyEvent()` method to report Jitney event.\"","timestamp":1592567083799,"type":""},{"level":"WARNING","message":"https://a0.muscache.com/airbnb/static/packages/9c0e-da28f557.js 1:62066 \"AirEvent has been deprecated, please consider using `logJitneyEvent()` method to report Jitney event.\"","timestamp":1592567085060,"type":""},{"level":"WARNING","message":"https://a0.muscache.com/airbnb/static/packages/9c0e-da28f557.js 1:62066 \"AirEvent has been deprecated, please consider using `logJitneyEvent()` method to report Jitney event.\"","timestamp":1592567085108,"type":""},{"level":"WARNING","message":"https://a0.muscache.com/airbnb/static/packages/9c0e-da28f557.js 1:62066 \"AirEvent has been deprecated, please consider using `logJitneyEvent()` method to report Jitney event.\"","timestamp":1592567085111,"type":""},{"level":"WARNING","message":"https://a0.muscache.com/airbnb/static/packages/9c0e-da28f557.js 1:62066 \"AirEvent has been deprecated, please consider using `logJitneyEvent()` method to report Jitney event.\"","timestamp":1592567086340,"type":""},{"level":"WARNING","message":"https://a0.muscache.com/airbnb/static/packages/9c0e-da28f557.js 1:62066 \"AirEvent has been deprecated, please consider using `logJitneyEvent()` method to report Jitney event.\"","timestamp":1592567087094,"type":""},{"level":"WARNING","message":"https://a0.muscache.com/airbnb/static/packages/9c0e-da28f557.js 1:62066 \"AirEvent has been deprecated, please consider using `logJitneyEvent()` method to report Jitney event.\"","timestamp":1592567087097,"type":""},{"level":"WARNING","message":"https://a0.muscache.com/airbnb/static/packages/9c0e-da28f557.js 1:62066 \"AirEvent has been deprecated, please consider using `logJitneyEvent()` method to report Jitney event.\"","timestamp":1592567087166,"type":""},{"level":"WARNING","message":"https://a0.muscache.com/airbnb/static/packages/9c0e-da28f557.js 1:62066 \"AirEvent has been deprecated, please consider using `logJitneyEvent()` method to report Jitney event.\"","timestamp":1592567096356,"type":""},{"level":"WARNING","message":"https://a0.muscache.com/airbnb/static/packages/9c0e-da28f557.js 1:62066 \"AirEvent has been deprecated, please consider using `logJitneyEvent()` method to report Jitney event.\"","timestamp":1592567097101,"type":""},{"level":"WARNING","message":"https://a0.muscache.com/airbnb/static/packages/9c0e-da28f557.js 1:62066 \"AirEvent has been deprecated, please consider using `logJitneyEvent()` method to report Jitney event.\"","timestamp":1592567097106,"type":""},{"level":"WARNING","message":"https://a0.muscache.com/airbnb/static/packages/9c0e-da28f557.js 1:62066 \"AirEvent has been deprecated, please consider using `logJitneyEvent()` method to report Jitney event.\"","timestamp":1592567097170,"type":""},{"level":"WARNING","message":"https://a0.muscache.com/airbnb/static/packages/9c0e-da28f557.js 1:62066 \"AirEvent has been deprecated, please consider using `logJitneyEvent()` method to report Jitney event.\"","timestamp":1592567106346,"type":""},{"level":"WARNING","message":"https://a0.muscache.com/airbnb/static/packages/9c0e-da28f557.js 1:62066 \"AirEvent has been deprecated, please consider using `logJitneyEvent()` method to report Jitney event.\"","timestamp":1592567107106,"type":""},{"level":"WARNING","message":"https://a0.muscache.com/airbnb/static/packages/9c0e-da28f557.js 1:62066 \"AirEvent has been deprecated, please consider using `logJitneyEvent()` method to report Jitney event.\"","timestamp":1592567107107,"type":""},{"level":"WARNING","message":"https://a0.muscache.com/airbnb/static/packages/9c0e-da28f557.js 1:62066 \"AirEvent has been deprecated, please consider using `logJitneyEvent()` method to report Jitney event.\"","timestamp":1592567107176,"type":""},{"level":"WARNING","message":"https://a0.muscache.com/airbnb/static/packages/9c0e-da28f557.js 1:62066 \"AirEvent has been deprecated, please consider using `logJitneyEvent()` method to report Jitney event.\"","timestamp":1592567108430,"type":""},{"level":"WARNING","message":"https://a0.muscache.com/airbnb/static/packages/9c0e-da28f557.js 1:62066 \"AirEvent has been deprecated, please consider using `logJitneyEvent()` method to report Jitney event.\"","timestamp":1592567108675,"type":""},{"level":"WARNING","message":"https://a0.muscache.com/airbnb/static/packages/9c0e-da28f557.js 1:62066 \"AirEvent has been deprecated, please consider using `logJitneyEvent()` method to report Jitney event.\"","timestamp":1592567109347,"type":""},{"level":"WARNING","message":"https://www.airbnb.co.in/ - A cookie associated with a cross-site resource at https://airbnb.co.in/ was set without the `SameSite` attribute. A future release of Chrome will only deliver cookies with cross-site requests if they are set with `SameSite=None` and `Secure`. You can review cookies in developer tools under Application>Storage>Cookies and see more details at https://www.chromestatus.com/feature/5088147346030592 and https://www.chromestatus.com/feature/5633521622188032.","timestamp":1592567109642,"type":""},{"level":"WARNING","message":"https://www.airbnb.co.in/ - A cookie associated with a cross-site resource at http://airbnb.co.in/ was set without the `SameSite` attribute. A future release of Chrome will only deliver cookies with cross-site requests if they are set with `SameSite=None` and `Secure`. You can review cookies in developer tools under Application>Storage>Cookies and see more details at https://www.chromestatus.com/feature/5088147346030592 and https://www.chromestatus.com/feature/5633521622188032.","timestamp":1592567109643,"type":""},{"level":"WARNING","message":"https://www.airbnb.co.in/ - A cookie associated with a cross-site resource at http://www.airbnb.co.in/ was set without the `SameSite` attribute. A future release of Chrome will only deliver cookies with cross-site requests if they are set with `SameSite=None` and `Secure`. You can review cookies in developer tools under Application>Storage>Cookies and see more details at https://www.chromestatus.com/feature/5088147346030592 and https://www.chromestatus.com/feature/5633521622188032.","timestamp":1592567109643,"type":""},{"level":"WARNING","message":"https://a0.muscache.com/airbnb/static/packages/9c0e-da28f557.js 1:62066 \"AirEvent has been deprecated, please consider using `logJitneyEvent()` method to report Jitney event.\"","timestamp":1592567112057,"type":""},{"level":"WARNING","message":"https://www.airbnb.co.in/ - A cookie associated with a cross-site resource at http://yahoo.com/ was set without the `SameSite` attribute. A future release of Chrome will only deliver cookies with cross-site requests if they are set with `SameSite=None` and `Secure`. You can review cookies in developer tools under Application>Storage>Cookies and see more details at https://www.chromestatus.com/feature/5088147346030592 and https://www.chromestatus.com/feature/5633521622188032.","timestamp":1592567112058,"type":""},{"level":"WARNING","message":"https://a0.muscache.com/airbnb/static/packages/9c0e-da28f557.js 1:62066 \"AirEvent has been deprecated, please consider using `logJitneyEvent()` method to report Jitney event.\"","timestamp":1592567113996,"type":""}],"screenShotFile":"00cd007a-0052-006a-001d-00ee005b00d9.png","timestamp":1592567108692,"duration":7967}
